Workbook

Sheet all_answers
A1: Respondent ID | B1: Public Administration (PA) or private company (PVT) | C1: Answer sent (Date/hour) | D1: Name (anonymised) | E1: Age range | F1: Mother Tongue | G1: Domain | H1: Domain tag (added by the researcher) | I1: Department tag (Added by the researcher) | J1: Work position | K1: Do you use translation tools in your working practice? | L1: If yes, which ones? | M1: What is your English level? | N1: What are your daily tasks? | O1: Daily tasks tag (added by the researcher) | P1: What types of text do you encounter in your daily work? | Q1: Text types tag (added by the researcher) | R1: What objectives? | S1: Goals tags (added by the researcher) | T1: What challenges? | U1: Frustrations tags (added by the researcher)
A2: 1 | B2: PA | C2: 45939.598 | D2: A | E2: 50-59 | F2: Catalan | G2: Sports (INEFC) | H2: Social policies (labour, sports, public affairs) | I2: Technical (economy, engineer, IT, sales) | J2: Senior Technician | K2: Yes | L2: Machine Translation (e.g. Google Translate, DeepL, other) | M2: Advanced | O2: None | P2: Related to research (reports, memos, emails, etc.) | Q2: Technical/scientific | S2: None | U2: None | AI2: =CONTA.SE('all_answers'!U:U; "
A3: 2 | B3: PA | C3: 45939.617 | D3: B | E3: 59-65 | F3: Spanish | G3: Barcelona City Council | H3: Administration (demograhic services) | I3: Management&leadership | J3: Head of Strategy Unit | K3: Yes | L3: Machine Translation (e.g. Google Translate, DeepL, other) | M3: B2 (Upper-intermediate) | O3: None | P3: Technical and popular science | Q3: Technical/scientific,Written informal | S3: None | U3: None
A4: 3 | B4: PA | C4: 45939.629 | D4: C | E4: 50-59 | F4: Catalan | G4: Education | H4: Education | I4: Social (communicatiion, education, health, HR) | J4: Professor | K4: Yes | L4: Machine Translation (e.g. Google Translate, DeepL, other) | M4: B1 (Intermediate) | O4: None | P4: Expository and argumentative texts | Q4: Education | S4: None | U4: None
A5: 4 | B5: PA | C5: 45939.652 | D5: D | E5: 59-65 | F5: Spanish | G5: Local Environmental Administration | H5: Administration (demograhic services) | I5: Management&leadership | J5: Head of Unit | K5: No | L5: None | M5: A1 (Elementary) | O5: None | P5: Administrative, technical | Q5: Administrative,Technical/scientific | S5: None | U5: None
A6: 5 | B6: PA | C6: 45939.655 | D6: E | E6: 40-49 | F6: Catalan | G6: Health | H6: Health | I6: Technical (economy, engineer, IT, sales) | J6: Specialist Technician | K6: Yes | L6: Machine Translation (e.g. Google Translate, DeepL, other) | M6: B2 (Upper-intermediate) | O6: None | P6: Scientific articles and materials from other countries | Q6: Technical/scientific | S6: None | U6: None
A7: 6 | B7: PA | C7: 45939.656 | D7: F | E7: 50-59 | F7: Catalan | G7: Department of Territory | H7: Infrastructures (transports) | I7: Management&leadership | J7: Project Manager | K7: No | L7: None | M7: B2 (Upper-intermediate) | O7: None | P7: Technical and administrative texts | Q7: Administrative,Technical/scientific | S7: None | U7: None
A8: 7 | B8: PA | C8: 45939.679 | D8: G | E8: 50-59 | F8: Spanish | G8: Autonomous University of Barcelona | H8: Education | I8: Administration | J8: Dean's Secretary | K8: Yes | L8: Machine Translation (e.g. Google Translate, DeepL, other) | M8: B2 (Upper-intermediate) | O8: None | P8: Formal and informal emails | Q8: Letters (formal and informal) | S8: None | U8: None
A9: 8 | B9: PA | C9: 45939.687 | D9: H | E9: 50-59 | F9: Spanish | G9: Legal Department | H9: Law | I9: Administration | J9: Lawyer | K9: Yes | L9: Artificial intelligence (e.g. ChatGPT, Gemini, Claude, DeepSeek, etc.) | M9: B2 (Upper-intermediate) | O9: None | P9: Administrative/legal | Q9: Administrative,Legal/economic | S9: None | U9: None
A10: 9 | B10: PA | C10: 45939.692 | D10: I | E10: 40-49 | F10: Catalan | G10: Green Infrastructure Environmental Management Office | H10: Environment | I10: Management&leadership | J10: Office Manager | K10: Yes | L10: Machine Translation (e.g. Google Translate, DeepL, other) | M10: B2 (Upper-intermediate) | O10: None | P10: Technical documents in Catalan | Q10: Technical/scientific | S10: None | U10: None
A11: 10 | B11: PA | C11: 45939.694 | D11: J | E11: 50-59 | F11: Catalan | G11: Agriculture | H11: Environment | I11: Technical (economy, engineer, IT, sales) | J11: Agricultural Technical Engineer | K11: Yes | L11: Machine Translation (e.g. Google Translate, DeepL, other) | M11: A1 (Elementary) | O11: None | P11: I normally use the translation for direct contact with a foreign user | Q11: Letters (formal and informal) | S11: None | U11: None
A12: 11 | B12: PA | C12: 45939.817 | D12: K | E12: 59-65 | F12: Catalan | G12: Territory, Housing and Ecological Transition | H12: Infrastructures (transports) | I12: Technical (economy, engineer, IT, sales) | J12: Technician | K12: Yes | L12: Intranet linguistic tools | M12: B2 (Upper-intermediate) | O12: None | P12: Technical documents, projects, administrative documents | Q12: Administrative,Technical/scientific | S12: None | U12: None
A13: 12 | B13: PA | C13: 45942.495 | D13: L | E13: 50-59 | F13: Catalan | G13: Department of Culture | H13: Culture | I13: Management&leadership | J13: Area Director | K13: Yes | L13: Machine Translation (e.g. Google Translate, DeepL, other) | M13: B2 (Upper-intermediate) | O13: None | P13: Explanatory texts for training courses | Q13: Education,Written informal | S13: None | U13: None
A14: 13 | B14: PA | C14: 14/10/2025 13.09.26 | D14: M | E14: 59-65 | F14: Italian | G14: Economy | H14: Economics | I14: Management&leadership | J14: Manager | K14: Yes | L14: Machine Translation (e.g. Google Translate, DeepL, other) | M14: Advanced | N14: Administrative and accounting tasks | O14: administrative,economic | P14: Legal-Economic | Q14: Legal/economic | R14: To research specialist terminology in relation to the texts to be translated. | S14: Terminology | T14: Selecting the most appropriate technical term | U14: Terminology
A15: 14 | B15: PA | C15: 22/10/2025 17.58.58 | D15: N | E15: 50-59 | F15: Italian | G15: Finance Department | H15: Economics | I15: Management&leadership | J15: Head | K15: No | L15: None | M15: A2 (Pre-intermediate) | N15: Financial management of the organisation, administrative documents | O15: administrative,economic | P15: Communications, business letters, administrative measures | Q15: Administrative,Letters (formal and informal) | R15: I don't use this tool. | S15: Don't use | T15: I do not use this tool | U15: Don't use
A16: 15 | B16: PA | C16: 25/10/2025 9.03.10 | D16: O | E16: 50-59 | F16: Italian | G16: Demographic Services | H16: Administration (demograhic services) | I16: Administration | J16: Administrative Instructor | K16: Yes | L16: Machine Translation (e.g. Google Translate, DeepL, other) | M16: Advanced | N16: Issuing documents and certificates | O16: administrative | P16: Certificates, applications, declarations | Q16: Administrative | R16: To help my interlocutor understand what I am asking. | S16: Understand/be understood | T16: Verifying the accuracy of the translation based on context and end use | U16: Accuracy/gram,Verify translation
A17: 16 | B17: PA | C17: 25/10/2025 9.17.35 | D17: P | E17: 50-59 | F17: Italian | G17: Municipal Public Relations Office | H17: Social policies (labour, sports, public affairs) | I17: Administration | J17: Executive Clerk | K17: Yes | L17: Machine Translation (e.g. Google Translate, DeepL, other) | M17: B1 (Intermediate) | N17: Public relations, facilitating access to municipal services | O17: correspondence (written and oral) | P17: Practical information for foreign citizens | Q17: Written informal | R17: To give correct information to foreign citizens who come to our help desk. | S17: Accuracy/true/correctness | T17: I am not sure | U17: Don't know
A18: 17 | B18: PA | C18: 25/10/2025 9.17.56 | D18: Q | E18: 59-65 | F18: Italian | G18: Public Administration | H18: Administration (demograhic services) | I18: Administration | J18: Clerk | K18: No | L18: None | M18: A2 (Pre-intermediate) | N18: Demographic services | O18: administrative | P18: None | Q18: None | R18: To understand properly. | S18: Understand/be understood | T18: None | U18: None
A19: 18 | B19: PA | C19: 25/10/2025 9.50.46 | D19: R | E19: 50-59 | F19: Italian | G19: Demographic Services | H19: Administration (demograhic services) | I19: Administration | J19: Public Official | K19: No | L19: None | M19: B2 (Upper-intermediate) | N19: CIE (Foreigners Identification Card), certificates, affidavits, residences, etc. | O19: administrative | P19: Ministry forms | Q19: Administrative | R19: I don't do it, but if I did, accuracy would be essential. | S19: Accuracy/true/correctness,Don't use | T19: I am not sure because I do not use machine translation | U19: Don't know
A20: 19 | B20: PA | C20: 25/10/2025 10.26.02 | D20: S | E20: 50-59 | F20: Italian | G20: Demographic Services | H20: Administration (demograhic services) | I20: Administration | J20: Organisational position | K20: Yes | L20: Machine Translation (e.g. Google Translate, DeepL, other) | M20: B1 (Intermediate) | N20: Various | O20: None | P20: Spoken | Q20: Oral | R20: To interact with the public. | S20: Understand/be understood | T20: Verifying accuracy | U20: Accuracy/gram,Verify translation
A21: 20 | B21: PA | C21: 25/10/2025 14.29.04 | D21: T | E21: 50-59 | F21: Italian | G21: Local Authorities | H21: Administration (demograhic services) | I21: Administration | J21: Administrative Instructor | K21: No | L21: None | M21: A1 (Elementary) | N21: Administrative acts | O21: administrative | P21: Texts in Italian | Q21: Written informal | R21: I don't do machine translations | S21: Don't use | T21: I do not use machine translation | U21: Don't use
A22: 21 | B22: PA | C22: 25/10/2025 14.38.25 | D22: U | E22: 50-59 | F22: Italian | G22: Local Health Authority | H22: Health | I22: Administration | J22: Administrative Assistant | K22: No | L22: None | M22: A2 (Pre-intermediate) | N22: Administrative | O22: administrative | P22: Social report | Q22: Written informal | R22: I don't do it | S22: Don't use | T22: It does not happen to me | U22: None
A23: 22 | B23: PA | C23: 25/10/2025 16.34.36 | D23: V | E23: 30-39 | F23: Italian | G23: Registry Office | H23: Administration (demograhic services) | I23: Administration | J23: Administrative Instructor | K23: Yes | L23: Machine Translation (e.g. Google Translate, DeepL, other) | M23: B1 (Intermediate) | N23: Changes of residence | O23: administrative | P23: Family applications | Q23: Administrative | R23: That everything is accurate | S23: Accuracy/true/correctness | T23: Some words are not translated | U23: Untranslated
A24: 23 | B24: PA | C24: 12/11/2025 17.15.03 | D24: X | E24: 30-39 | F24: Spanish | G24: Education | H24: Education | I24: Social (communicatiion, education, health, HR) | J24: Teacher | K24: Yes | L24: Artificial intelligence (e.g. ChatGPT, Gemini, Claude, DeepSeek, etc.) | M24: B2 (Upper-intermediate) | N24: Reading, comprehension and calculation activities | O24: educational | P24: Scientific | Q24: Technical/scientific | R24: Speed and ease of understanding | S24: Speed,Understand/be understood | T24: Some grammatical errors | U24: Accuracy/gram
A25: 24 | B25: PA | C25: 12/11/2025 18.09.16 | D25: Y | E25: 30-39 | F25: Spanish | G25: Security | H25: Defense | I25: Administration | J25: Police Officer | K25: No | L25: Machine Translation (e.g. Google Translate, DeepL, other) | M25: B1 (Intermediate) | N25: Administrative | O25: administrative | P25: None | Q25: None | R25: Immediate translation | S25: Speed | T25: I don't use it much | U25: Don't use
... A31: 30 | B31: PVT | C31: 16/11/2025 10.19.33 | D31: AE | E31: 18-29 | F31: Italian | G31: Research & Development | H31: IT | I31: Technical (economy, engineer, IT, sales) | J31: Trainee in Language Technologies (Eurac Research) | K31: Yes | L31: Machine Translation (e.g. Google Translate, DeepL, other) | M31: Advanced | N31: I am currently working on prototyping LLM and models trained in-house on spell checking of texts in German L2 | O31: scientific | P31: IT documentation | Q31: Technical/scientific | R31: To get an idea (even if only a rough one) of the meaning of a given text | S31: Understand/be understood | T31: Terminological inconsistency | U31: Terminology
A32: 31 | B32: PA | C32: 45980.659 | D32: AF | E32: 40-49 | F32: Catalan | G32: Strategic Planning | H32: Technical | I32: Technical (economy, engineer, IT, sales) | J32: Technician | K32: Yes | L32: Machine Translation (e.g. Google Translate, DeepL, other) | M32: Advanced | N32: Definition, planning and evaluation of projects (in summary) | O32: management | P32: Administrative and technical documents, formal tone | Q32: Administrative,Technical/scientific | R32: Normally, it is to check that the text in English or French is correct, or to rethink it | S32: Revision | T32: Sometimes it doesn't understand exactly what I want to convey | U32: Understand/be understood
A33: 32 | B33: PVT | C33: 45980.762 | D33: AG | E33: 40-49 | F33: Spanish | G33: Sales | H33: Marketing | I33: Management&leadership | J33: Company Administrator | K33: No | L33: Machine Translation (e.g. Google Translate, DeepL, other) | M33: Advanced | N33: Communicating with clients and suppliers | O33: correspondence (written and oral) | P33: Specific to our sector | Q33: Technical/scientific | R33: To correct the text to explain myself better | S33: Revision | T33: so that it is understood | U33: Understand/be understood
A34: 33 | B34: PA | C34: 45981.536 | D34: AH | E34: 59-65 | F34: Spanish | G34: Street cleaning, waste collection and circular economy | H34: Environment | I34: Technical (economy, engineer, IT, sales) | J34: Technician | K34: Yes | L34: None | M34: A2 (Pre-intermediate) | N34: Working, reading | O34: technical | P34: Maps and charts | Q34: Graphical | R34: I don't do it | S34: Don't use | T34: I don't do it | U34: Don't use
A35: 34 | B35: PVT | C35: 45981.65 | D35: AI | E35: 50-59 | F35: Catalan | G35: Production | H35: Technical | I35: Management&leadership | J35: Industrial Director | K35: Yes | L35: Machine Translation (e.g. Google Translate, DeepL, other) | M35: B2 (Upper-intermediate) | N35: Planning production, installing machines... | O35: management,technical | P35: Technical | Q35: Technical/scientific | R35: To translate manuals or correct emails from suppliers, clients or companies in other locations | S35: Revision | T35: Correct grammatical composition | U35: Accuracy/gram
A36: 35 | B36: PVT | C36: 19/11/2025 16.00.06 | D36: AJ | E36: 40-49 | F36: Spanish | G36: Digital marketing | H36: Marketing | I36: Social (communicatiion, education, health, HR) | J36: Digital Content Creator | K36: Yes | L36: Artificial intelligence (e.g. ChatGPT, Gemini, Claude, DeepSeek, etc.) | M36: Bilingual | N36: Video editing, creation of advertising campaigns. | O36: management,marketing | P36: Various topics depending on the client. | Q36: Technical/scientific | R36: Ensure that the result is as faithful as possible to the meaning. | S36: Accuracy/true/correctness | T36: Not knowing for sure if the result is adequate. | U36: Accuracy/gram
A37: 36 | B37: PVT | C37: 19/11/2025 16.05.24 | D37: AK | E37: 40-49 | F37: Spanish | G37: Software engineering | H37: IT | I37: Management&leadership | J37: Senior | K37: Yes | L37: Artificial intelligence (e.g. ChatGPT, Gemini, Claude, DeepSeek, etc.) | M37: Advanced | N37: Engineering and documentation | O37: administrative,technical | P37: Technical text | Q37: Technical/scientific | R37: Above all, correct | S37: Revision | T37: That it conveys the ideas correctly | U37: Accuracy/gram
A38: 37 | B38: PVT | C38: 19/11/2025 17.48.18 | D38: AL | E38: 40-49 | F38: Spanish/Catalan | G38: Biotechnology in the USA | H38: Health | I38: Management&leadership | J38: Human Resources and Operations Head | K38: No | L38: Artificial intelligence (e.g. ChatGPT, Gemini, Claude, DeepSeek, etc.) | M38: Advanced | N38: Many emails and short texts. | O38: correspondence (written and oral) | P38: Emails, contract review | Q38: Legal/economic,Letters (formal and informal) | R38: Reduce syntax and grammatical errors | S38: Accuracy/true/correctness | T38: The tone and style differ from my intention | U38: Style and tone
A39: 38 | B39: PVT | C39: 19/11/2025 21.34.51 | D39: AM | E39: 40-49 | F39: Catalan | G39: Veterinary medicine | H39: Health | I39: Management&leadership | J39: Centre Manager | K39: Yes | L39: None | M39: Advanced | N39: Behavioural visits and sessions with dogs | O39: scientific | P39: Scientific books | Q39: Technical/scientific | R39: I don't use it | S39: Don't use | T39: I don't have any | U39: Don't use
A40: 39 | B40: PVT | C40: 19/11/2025 17.54.27 | D40: AN | E40: 40-49 | F40: Spanish | G40: Publishing | H40: Marketing | I40: Management&leadership | J40: Social Media Manager | K40: No | L40: Artificial intelligence (e.g. ChatGPT, Gemini, Claude, DeepSeek, etc.) | M40: Advanced | N40: Presentations on social media strategy and management | O40: management,marketing | P40: All kinds. Especially social media posts, synopses, press release notes, communication and marketing plans, video scripts | Q40: All,Written informal | R40: Speed | S40: Speed | T40: I have to check the translation for possible errors | U40: Verify translation
A41: 40 | B41: PVT | C41: 21/11/2025 12.23.34 | D41: AM | E41: 18-29 | F41: Italian | G41: Tourism | H41: Tourism | I41: Social (communicatiion, education, health, HR) | J41: Barista | K41: Yes | L41: None | M41: Advanced | N41: Cafeteria and customer care | O41: correspondence (written and oral) | P41: Orders | Q41: Written informal | R41: How to say something I can't remember | S41: writing support | T41: The internet connection | U41: internet connection
A42: 41 | B42: PVT | C42: 21/11/2025 14.26.30 | D42: AO | E42: 40-49 | F42: Italian | G42: IT | H42: IT | I42: Management&leadership | J42: Manager | K42: Yes | L42: Machine Translation (e.g. Google Translate, DeepL, other) | M42: B2 (Upper-intermediate) | N42: Coordination and control | O42: management | P42: Contracts | Q42: Legal/economic | R42: Simplify understanding | S42: Understand/be understood | T42: Free tools with low quality levels | U42: free tools,low quality
A43: 42 | B43: PVT | C43: 22/11/2025 15.10.18 | D43: AP | E43: 30-39 | F43: Italian | G43: Digital marketing | H43: Marketing | I43: Management&leadership | J43: Co-Founder | K43: Yes | L43: Artificial intelligence (e.g. ChatGPT, Gemini, Claude, DeepSeek, etc.) | M43: Advanced | N43: Campaign management, coordination of freelancers, customer contact | O43: correspondence (written and oral),management | P43: Content creation for campaigns and emails | Q43: Graphical,Letters (formal and informal) | R43: A translation that is as close as possible to the actual meaning in the original language. | S43: Accuracy/true/correctness | T43: Literal translation or processing completely different from the initial content provided | U43: Accuracy/gram,literal translation
A44: 43 | B44: PVT | C44: 23/11/2025 19.41.47 | D44: AQ | E44: 30-39 | F44: Italian | G44: Toys | H44: Games | I44: Management&leadership | J44: Category Manager | K44: Yes | L44: None | M44: Advanced | N44: Sales data analysis, competition analysis, performance analysis of the relevant product category, definition of product costs and related margins and retail prices, evaluating the product life cycle. Definition of sales and promotional materials, creation of sales catalogues. | O44: management,marketing | P44: B2B texts | Q44: Technical/scientific | R44: Make it as realistic as possible and appropriate for the remuneration. | S44: Accuracy/true/correctness | T44: That it uses the correct terms and is understandable and makes sense in the final language, without using literal translations | U44: Terminology,Understand/be understood,literal translation
A45: 44 | B45: PVT | C45: 01/12/2025 19.36.43 | D45: AR | E45: 30-39 | F45: Spanish | G45: My previous job, Translation. | H45: Technical | I45: Management&leadership | J45: Senior Business Manager | K45: Yes | L45: Both | M45: B2 (Upper-intermediate) | N45: Content generation, commercial activities such as attending events, preparing commercial proposals, etc. | O45: management,marketing | P45: Related to the service I offer | Q45: Written informal | R45: Ensure that the message is understood and appropriate. | S45: Accuracy/true/correctness,Understand/be understood | T45: The accuracy of the message I want to convey, the appropriateness of the tone, and the correct use of regionalisms, so that it is natural and fluid, and connects with the audience. | U45: Accuracy/gram,Style and tone,Understand/be understood

Sheet Results
A1: PA/PVT | B1: Count | C1: % | D1: Age range | E1: Count | F1: % | G1: Mother tongue | H1: Count | I1: % | J1: Domain | K1: Count | L1: % | M1: Work position | N1: Count | O1: % | P1: Translation use | Q1: Count | R1: % | S1: Which tools | T1: Count | U1: % | V1: English level | W1: Count | X1: % | Y1: Daily tasks (tags) | Z1: Count | AA1: % | AB1: Text types (tags) | AC1: Count | AD1: % | AE1: Goals (tags) | AF1: Count | AG1: % | AH1: Frustrations (tags) | AI1: Count | AJ1: %
A2: Public administration | B2: =COUNTIF(all_answers!B:B, all_answers!B34) -> 30 | C2: =_xlfn.PERCENTOF(B2,B4) -> 0.68181818 | D2: 50-59 | E2: =COUNTIF(all_answers!E:E, D2) -> 15 | F2: =_xlfn.PERCENTOF(E2,$E$7) -> 0.34090909 | G2: Spanish | H2: =COUNTIF(all_answers!F:F, "*Spanish*")+COUNTIF(all_answers!F:F, "*Catalan*") -> 27 | I2: =_xlfn.PERCENTOF(H2,$H$4) -> 0.6 | J2: Administration (demograhic services) | K2: =COUNTIF(all_answers!H:H, J2) -> 9 | L2: =_xlfn.PERCENTOF(K2,$K$17) -> 0.20454545 | M2: Management&leadership | N2: =COUNTIF(all_answers!I:I, Results!M2) -> 19 | O2: =_xlfn.PERCENTOF(N2, $N$6) -> 0.43181818 | P2: Yes | Q2: =COUNTIF(all_answers!K:K, "yes") -> 33 | R2: =_xlfn.PERCENTOF(Q2,$Q$4) -> 0.75 | S2: MT | T2: =COUNTIF(all_answers!L:L, all_answers!L23) + COUNTIF(all_answers!L:L,all_answers!L45) -> 22 | U2: =_xlfn.PERCENTOF(T2,$T$7) -> 0.48888889 | V2: C | W2: =COUNTIF(all_answers!M:M, all_answers!M39) -> 15 | X2: =_xlfn.PERCENTOF(W2, $W$8) -> 0.34090909 | Y2: administrative | Z2: =COUNTIF(all_answers!O:O, "*administrative*") -> 11 | AA2: =_xlfn.PERCENTOF(Z2, $Z$11) -> 0.2 | AB2: Technical/scientific | AC2: =COUNTIF(all_answers!Q:Q, "*Technical/scientific*") -> 17 | AD2: =_xlfn.PERCENTOF(AC2, $AC$11) -> 0.31481481 | AE2: Accuracy/true/correctness | AF2: =COUNTIF(all_answers!S:S, "*Accuracy/true/correctness*") -> 9 | AG2: =_xlfn.PERCENTOF(AF2,$AF$11) -> 0.19148936 | AH2: Accuracy/gram | AI2: =COUNTIF(all_answers!U:U, "*Accuracy/gram*") -> 9 | AJ2: =_xlfn.PERCENTOF(AI2, $AI$16) -> 0.16981132
A3: Private company | B3: =COUNTIF(all_answers!B:B, all_answers!B40) -> 14 | C3: =_xlfn.PERCENTOF(B3,B4) -> 0.31818182 | D3: 30-39 | E3: =COUNTIF(all_answers!E:E, D3) -> 11 | F3: =_xlfn.PERCENTOF(E3,$E$7) -> 0.25 | G3: Italian | H3: =COUNTIF(all_answers!F:F, "Italian") -> 18 | I3: =_xlfn.PERCENTOF(H3,$H$4) -> 0.4 | J3: Education | K3: =COUNTIF(all_answers!H:H, J3) -> 6 | L3: =_xlfn.PERCENTOF(K3,$K$17) -> 0.13636364 | M3: Administration | N3: =COUNTIF(all_answers!I:I, Results!M3) -> 12 | O3: =_xlfn.PERCENTOF(N3, $N$6) -> 0.27272727 | P3: No | Q3: =COUNTIF(all_answers!K:K, "no") -> 11 | R3: =_xlfn.PERCENTOF(Q3,$Q$4) -> 0.25 | S3: LLM | T3: =COUNTIF(all_answers!L:L, all_answers!L28) + COUNTIF(all_answers!L:L,all_answers!L45) -> 10 | U3: =_xlfn.PERCENTOF(T3,$T$7) -> 0.22222222 | V3: B2 | W3: =COUNTIF(all_answers!M:M, all_answers!M35) -> 13 | X3: =_xlfn.PERCENTOF(W3, $W$8) -> 0.29545455 | Y3: management | Z3: =COUNTIF(all_answers!O:O, "*management*") -> 8 | AA3: =_xlfn.PERCENTOF(Z3, $Z$11) -> 0.14545455 | AB3: Administrative | AC3: =COUNTIF(all_answers!Q:Q, "*Administrative*") -> 11 | AD3: =_xlfn.PERCENTOF(AC3, $AC$11) -> 0.2037037 | AE3: Understand/be understood | AF3: =COUNTIF(all_answers!S:S, "*Understand/be understood*") -> 9 | AG3: =_xlfn.PERCENTOF(AF3,$AF$11) -> 0.19148936 | AH3: Understand/be understood | AI3: =COUNTIF(all_answers!U:U, "*Understand/be understood*") -> 5 | AJ3: =_xlfn.PERCENTOF(AI3, $AI$16) -> 0.094339623
A4: TOT | B4: =SUM(B2:B3) -> 44 | D4: 40-49 | E4: =COUNTIF(all_answers!E:E, D4) -> 10 | F4: =_xlfn.PERCENTOF(E4,$E$7) -> 0.22727273 | G4: TOT | H4: =SUM(H2:H3) -> 45 | J4: Health | K4: =COUNTIF(all_answers!H:H, J4) -> 4 | L4: =_xlfn.PERCENTOF(K4,$K$17) -> 0.090909091 | M4: Technical (economy, engineer, IT, sales) | N4: =COUNTIF(all_answers!I:I, Results!M4) -> 7 | O4: =_xlfn.PERCENTOF(N4, $N$6) -> 0.15909091 | P4: TOT | Q4: =SUM(Q2:Q3) -> 44 | S4: None | T4: =COUNTIF(all_answers!L:L, all_answers!L44) -> 11 | U4: =_xlfn.PERCENTOF(T4,$T$7) -> 0.24444444 | V4: B1 | W4: =COUNTIF(all_answers!M:M, all_answers!M30) -> 8 | X4: =_xlfn.PERCENTOF(W4, $W$8) -> 0.18181818 | Y4: marketing | Z4: =COUNTIF(all_answers!O:O, "*marketing*") -> 6 | AA4: =_xlfn.PERCENTOF(Z4, $Z$11) -> 0.10909091 | AB4: Written informal | AC4: =COUNTIF(all_answers!Q:Q, "*Written informal*") -> 8 | AD4: =_xlfn.PERCENTOF(AC4, $AC$11) -> 0.14814815 | AE4: Don't use | AF4: =COUNTIF(all_answers!S:S, "*don't use*") -> 6 | AG4: =_xlfn.PERCENTOF(AF4,$AF$11) -> 0.12765957 | AH4: terminology | AI4: =COUNTIF(all_answers!U:U, "*terminology*") -> 5 | AJ4: =_xlfn.PERCENTOF(AI4, $AI$16) -> 0.094339623
D5: 59-65 | E5: =COUNTIF(all_answers!E:E, D5) -> 6 | F5: =_xlfn.PERCENTOF(E5,$E$7) -> 0.13636364 | H5: (1 person is bilingual) | J5: Marketing | K5: =COUNTIF(all_answers!H:H, J5) -> 4 | L5: =_xlfn.PERCENTOF(K5,$K$17) -> 0.090909091 | M5: Social (communicatiion, education, health, HR) | N5: =COUNTIF(all_answers!I:I, Results!M5) -> 6 | O5: =_xlfn.PERCENTOF(N5, $N$6) -> 0.13636364 | S5: Intranet linguistic tools | T5: =COUNTIF(all_answers!L:L, all_answers!L12) -> 1 | U5: =_xlfn.PERCENTOF(T5,$T$7) -> 0.022222222 | V5: A2 | W5: =COUNTIF(all_answers!M:M, all_answers!M34) -> 4 | X5: =_xlfn.PERCENTOF(W5, $W$8) -> 0.090909091 | Y5: correspondence (written and oral) | Z5: =COUNTIF(all_answers!O:O, "*correspondence (written and oral)*") -> 5 | AA5: =_xlfn.PERCENTOF(Z5, $Z$11) -> 0.090909091 | AB5: letters (formal and informal) | AC5: =COUNTIF(all_answers!Q:Q, "*letters (formal and informal)*") -> 5 | AD5: =_xlfn.PERCENTOF(AC5, $AC$11) -> 0.092592593 | AE5: Revision | AF5: =COUNTIF(all_answers!S:S, "*revision*") -> 4 | AG5: =_xlfn.PERCENTOF(AF5,$AF$11) -> 0.085106383 | AH5: Verify translation | AI5: =COUNTIF(all_answers!U:U, "*Verify translation*") -> 3 | AJ5: =_xlfn.PERCENTOF(AI5, $AI$16) -> 0.056603774
D6: 18-29 | E6: =COUNTIF(all_answers!E:E, D6) -> 2 | F6: =_xlfn.PERCENTOF(E6,$E$7) -> 0.045454545 | J6: Environment | K6: =COUNTIF(all_answers!H:H, J6) -> 3 | L6: =_xlfn.PERCENTOF(K6,$K$17) -> 0.068181818 | M6: TOT | N6: =SUM(N2:N5) -> 44 | S6: Sight translation, Terminology research | T6: =COUNTIF(all_answers!L:L, all_answers!L29) -> 1 | U6: =_xlfn.PERCENTOF(T6,$T$7) -> 0.022222222 | V6: A1 | W6: =COUNTIF(all_answers!M:M, all_answers!M21) -> 3 | X6: =_xlfn.PERCENTOF(W6, $W$8) -> 0.068181818 | Y6: economic | Z6: =COUNTIF(all_answers!O:O, "*economic*") -> 3 | AA6: =_xlfn.PERCENTOF(Z6, $Z$11) -> 0.054545455 | AB6: legal/economic | AC6: =COUNTIF(all_answers!Q:Q, "*legal/economic*") -> 4 | AD6: =_xlfn.PERCENTOF(AC6, $AC$11) -> 0.074074074 | AE6: Speed | AF6: =COUNTIF(all_answers!S:S, "*speed*") -> 3 | AG6: =_xlfn.PERCENTOF(AF6,$AF$11) -> 0.063829787 | AH6: Style and tone | AI6: =COUNTIF(all_answers!U:U, "*Style and tone*") -> 2 | AJ6: =_xlfn.PERCENTOF(AI6, $AI$16) -> 0.037735849
D7: TOT | E7: =SUM(E2:E6) -> 44 | J7: Social policies (labour, sports, public affairs) | K7: =COUNTIF(all_answers!H:H, J7) -> 3 | L7: =_xlfn.PERCENTOF(K7,$K$17) -> 0.068181818 | S7: TOT | T7: =SUM(T2:T6) -> 45 | V7: Native/bilingual | W7: =COUNTIF(all_answers!M:M, all_answers!M36) -> 1 | X7: =_xlfn.PERCENTOF(W7, $W$8) -> 0.022727273 | Y7: education | Z7: =COUNTIF(all_answers!O:O, "*education*") -> 3 | AA7: =_xlfn.PERCENTOF(Z7, $Z$11) -> 0.054545455 | AB7: none | AC7: =COUNTIF(all_answers!Q:Q, "*none*") -> 3 | AD7: =_xlfn.PERCENTOF(AC7, $AC$11) -> 0.055555556 | AE7: Terminology | AF7: =COUNTIF(all_answers!S:S, "*terminology*") -> 2 | AG7: =_xlfn.PERCENTOF(AF7,$AF$11) -> 0.042553191 | AH7: literal translation | AI7: =COUNTIF(all_answers!U:U, "*literal translation*") -> 2 | AJ7: =_xlfn.PERCENTOF(AI7, $AI$16) -> 0.037735849
J8: IT | K8: =COUNTIF(all_answers!H:H, J8) -> 3 | L8: =_xlfn.PERCENTOF(K8,$K$17) -> 0.068181818 | T8: 1 person put "both" | V8: TOT | W8: =SUM(W2:W7) -> 44 | Y8: scientific | Z8: =COUNTIF(all_answers!O:O, "*scientific*") -> 3 | AA8: =_xlfn.PERCENTOF(Z8, $Z$11) -> 0.054545455 | AB8: Graphical | AC8: =COUNTIF(all_answers!Q:Q, "*graphical*") -> 2 | AD8: =_xlfn.PERCENTOF(AC8, $AC$11) -> 0.037037037 | AE8: Generation/information | AF8: =COUNTIF(all_answers!S:S, "*generation/information*") -> 1 | AG8: =_xlfn.PERCENTOF(AF8,$AF$11) -> 0.021276596 | AH8: Untranslated | AI8: =COUNTIF(all_answers!U:U, "*Untranslated*") -> 1 | AJ8: =_xlfn.PERCENTOF(AI8, $AI$16) -> 0.018867925
J9: Technical | K9: =COUNTIF(all_answers!H:H,J9) -> 3 | L9: =_xlfn.PERCENTOF(K9,$K$17) -> 0.068181818 | Y9: technical | Z9: =COUNTIF(all_answers!O:O, "*technical*") -> 3 | AA9: =_xlfn.PERCENTOF(Z9, $Z$11) -> 0.054545455 | AB9: Education | AC9: =COUNTIF(all_answers!Q:Q, "*education*") -> 2 | AD9: =_xlfn.PERCENTOF(AC9, $AC$11) -> 0.037037037 | AE9: writing support | AF9: =COUNTIF(all_answers!S:S, "*writing support*") -> 1 | AG9: =_xlfn.PERCENTOF(AF9,$AF$11) -> 0.021276596 | AH9: Context | AI9: =COUNTIF(all_answers!U:U, "*Context*") -> 1 | AJ9: =_xlfn.PERCENTOF(AI9, $AI$16) -> 0.018867925
J10: Infrastructures (transports) | K10: =COUNTIF(all_answers!H:H, J10) -> 2 | L10: =_xlfn.PERCENTOF(K10,$K$17) -> 0.045454545 | Y10: none | Z10: =COUNTIF(all_answers!O:O, "*none*") -> 13 | AA10: =_xlfn.PERCENTOF(Z10, $Z$11) -> 0.23636364 | AB10: All | AC10: =COUNTIF(all_answers!Q:Q, "*all*") -> 2 | AD10: =_xlfn.PERCENTOF(AC10, $AC$11) -> 0.037037037 | AE10: None | AF10: =COUNTIF(all_answers!S:S, "*none*") -> 12 | AG10: =_xlfn.PERCENTOF(AF10,$AF$11) -> 0.25531915 | AH10: internet connection | AI10: =COUNTIF(all_answers!U:U, "*internet connection*") -> 1 | AJ10: =_xlfn.PERCENTOF(AI10, $AI$16) -> 0.018867925
J11: Economics | K11: =COUNTIF(all_answers!H:H, J11) -> 2 | L11: =_xlfn.PERCENTOF(K11,$K$17) -> 0.045454545 | Y11: TOT | Z11: =SUM(Z2:Z10) -> 55 | AB11: TOT | AC11: =SUM(AC2:AC10) -> 54 | AE11: TOT | AF11: =SUM(AF2:AF10) -> 47 | AH11: free tools | AI11: =COUNTIF(all_answers!U:U, "*free tools*") -> 1 | AJ11: =_xlfn.PERCENTOF(AI11, $AI$16) -> 0.018867925
J12: Law | K12: =COUNTIF(all_answers!H:H, J12) -> 1 | L12: =_xlfn.PERCENTOF(K12,$K$17) -> 0.022727273 | Z12: more than 1 possible answer | AC12: more than 1 possible answer | AF12: more than 1 possible answer | AH12: low quality | AI12: =COUNTIF(all_answers!U:U, "*low quality*") -> 1 | AJ12: =_xlfn.PERCENTOF(AI12, $AI$16) -> 0.018867925
J13: Culture | K13: =COUNTIF(all_answers!H:H, J13) -> 1 | L13: =_xlfn.PERCENTOF(K13,$K$17) -> 0.022727273 | AH13: Don't know | AI13: =COUNTIF(all_answers!U:U, "*Don't know*") -> 2 | AJ13: =_xlfn.PERCENTOF(AI13, $AI$16) -> 0.037735849
J14: Defense | K14: =COUNTIF(all_answers!H:H, J14) -> 1 | L14: =_xlfn.PERCENTOF(K14,$K$17) -> 0.022727273 | AH14: None | AI14: =COUNTIF(all_answers!U:U, "*none*") -> 15 | AJ14: =_xlfn.PERCENTOF(AI14, $AI$16) -> 0.28301887
J15: Tourism | K15: =COUNTIF(all_answers!H:H, J15) -> 1 | L15: =_xlfn.PERCENTOF(K15,$K$17) -> 0.022727273 | AH15: Don't use | AI15: =COUNTIF(all_answers!U:U, "*Don't use*") -> 5 | AJ15: =_xlfn.PERCENTOF(AI15, $AI$16) -> 0.094339623
J16: Games | K16: =COUNTIF(all_answers!H:H, J16) -> 1 | L16: =_xlfn.PERCENTOF(K16,$K$17) -> 0.022727273 | AH16: TOT | AI16: =SUM(AI2:AI15) -> 53
J17: TOT | K17: =SUM(K2:K16) -> 44 | AI17: more than 1 possible answer
AE19: TOTAL WITHOUT NONE, DON'T USE: | AF19: =SUM(AF11-AF10-AF4) -> 29 | AH19: TOTAL N. WITHOUT NONE, DON'T USE, DON'T KNOW: | AI19: =SUM(AI16-AI13-AI15-AI14) -> 31
AE20: Accuracy/true/correctness | AG20: =_xlfn.PERCENTOF(AF2, $AF$19) -> 0.31034483 | AH20: Accuracy/gram | AJ20: =_xlfn.PERCENTOF(AI2, $AI$19) -> 0.29032258
AE21: Understand/be understood | AG21: =_xlfn.PERCENTOF(AF3, $AF$19) -> 0.31034483 | AH21: Understand/be understood | AJ21: =_xlfn.PERCENTOF(AI3, $AI$19) -> 0.16129032
AE22: Terminology | AG22: =_xlfn.PERCENTOF(AF7, $AF$19) -> 0.068965517 | AH22: terminology | AJ22: =_xlfn.PERCENTOF(AI4, $AI$19) -> 0.16129032
AE23: Revision | AG23: =_xlfn.PERCENTOF(AF5, $AF$19) -> 0.13793103 | AH23: Verify translation | AJ23: =_xlfn.PERCENTOF(AI5, $AI$19) -> 0.096774194
AE24: Speed | AG24: =_xlfn.PERCENTOF(AF6, $AF$19) -> 0.10344828 | AH24: Style and tone | AJ24: =_xlfn.PERCENTOF(AI6, $AI$19) -> 0.064516129
AE25: Generation/information | AG25: =_xlfn.PERCENTOF(AF8, $AF$19) -> 0.034482759 | AH25: literal translation | AJ25: =_xlfn.PERCENTOF(AI7, $AI$19) -> 0.064516129
AE26: writing support | AG26: =_xlfn.PERCENTOF(AF9, $AF$19) -> 0.034482759 | AH26: Untranslated | AJ26: =_xlfn.PERCENTOF(AI8, $AI$19) -> 0.032258065
AH27: Context | AJ27: =_xlfn.PERCENTOF(AI9, $AI$19) -> 0.032258065
AH28: internet connection | AJ28: =_xlfn.PERCENTOF(AI10, $AI$19) -> 0.032258065
AH29: free tools | AJ29: =_xlfn.PERCENTOF(AI11, $AI$19) -> 0.032258065
AH30: low quality | AJ30: =_xlfn.PERCENTOF(AI12, $AI$19) -> 0.032258065
